[
    {
        "titulo_original": "Stranger Things",
        "tmdb_id": 66732,
        "tipo": "tv_episode",
        "season": 4,
        "episode": 1,
        "idioma": "ar",
        "pais": "SA",
        "nome_idioma": "Arabic",
        "titulo_traduzido": "فصل 1: نادي هيلفاير",
        "sinopse_traduzida": "تتعرّض \"إيل\" للتنمّر في مدرستها الجديدة لكنّها لا تستطيع الردّ، وتفتح \"جويس\" طردًا غامضًا. وفي \"هوكينز\"، تثير لاعبة مشاكسة ليلة \"دي أند دي\"."
    },
    {
        "titulo_original": "Stranger Things",
        "tmdb_id": 66732,
        "tipo": "tv_episode",
        "season": 4,
        "episode": 1,
        "idioma": "ar",
        "pais": "AE",
        "nome_idioma": "Arabic",
        "titulo_traduzido": "فصل 1: نادي هيلفاير",
        "sinopse_traduzida": "تتعرّض \"إيل\" للتنمّر في مدرستها الجديدة لكنّها لا تستطيع الردّ، وتفتح \"جويس\" طردًا غامضًا. وفي \"هوكينز\"، تثير لاعبة مشاكسة ليلة \"دي أند دي\"."
    },
    {
        "titulo_original": "Stranger Things",
        "tmdb_id": 66732,
        "tipo": "tv_episode",
        "season": 4,
        "episode": 1,
        "idioma": "bg",
        "pais": "BG",
        "nome_idioma": "Bulgarian",
        "titulo_traduzido": "Първа глава: Клубът на Адския огън",
        "sinopse_traduzida": ""
    },
    {
        "titulo_original": "Stranger Things",
        "tmdb_id": 66732,
        "tipo": "tv_episode",
        "season": 4,
        "episode": 1,
        "idioma": "bs",
        "pais": "BS",
        "nome_idioma": "Bosnian",
        "titulo_traduzido": "",
        "sinopse_traduzida": ""
    },
    {
        "titulo_original": "Stranger Things",
        "tmdb_id": 66732,
        "tipo": "tv_episode",
        "season": 4,
        "episode": 1,
        "idioma": "cs",
        "pais": "CZ",
        "nome_idioma": "Czech",
        "titulo_traduzido": "Kapitola první: Klub Hellfire",
        "sinopse_traduzida": "El na nové škole šikanují a ona se nemá jak bránit. Joyce otevírá tajemný balíček. V Hawkinsu zamíchá hubatá hráčka pořadím účastníků noční herní seance."
    },
    {
        "titulo_original": "Stranger Things",
        "tmdb_id": 66732,
        "tipo": "tv_episode",
        "season": 4,
        "episode": 1,
        "idioma": "da",
        "pais": "DK",
        "nome_idioma": "Danish",
        "titulo_traduzido": "Kap. 1: Hellfire-klubben",
        "sinopse_traduzida": "El bliver mobbet på sin nye skole, men kan ikke give igen. Joyce åbner en mystisk pakke, og hjemme i Hawkins skaber en benhård spiller røre til en D&D-aften."
    },
    {
        "titulo_original": "Stranger Things",
        "tmdb_id": 66732,
        "tipo": "tv_episode",
        "season": 4,
        "episode": 1,
        "idioma": "de",
        "pais": "DE",
        "nome_idioma": "German",
        "titulo_traduzido": "Kapitel eins: Der Höllenfeuer-Club",
        "sinopse_traduzida": "Elfie wird in der Schule gehänselt und kann sich nicht wehren. Joyce öffnet ein mysteriöses Paket. In Hawkins mischt eine schlagfertige Spielerin bei D&D mit."
    },
    {
        "titulo_original": "Stranger Things",
        "tmdb_id": 66732,
        "tipo": "tv_episode",
        "season": 4,
        "episode": 1,
        "idioma": "el",
        "pais": "GR",
        "nome_idioma": "Greek",
        "titulo_traduzido": "Κεφάλαιο πρώτο: Σύλλογος Χελφάιαρ",
        "sinopse_traduzida": "Η Εντ έχει νταήδες στο νέο της σχολείο, μα δεν περνά στην αντεπίθεση. Η Τζόις ανοίγει ένα παράξενο πακέτο. Πίσω στο Χόκινς, μια παίκτρια ταράζει τα νερά στη βραδιά D&D."
    },
    {
        "titulo_original": "Stranger Things",
        "tmdb_id": 66732,
        "tipo": "tv_episode",
        "season": 4,
        "episode": 1,
        "idioma": "en",
        "pais": "US",
        "nome_idioma": "English",
        "titulo_traduzido": "Chapter One: The Hellfire Club",
        "sinopse_traduzida": "El is bullied at school. Joyce opens a mysterious package. A scrappy player shakes up D&D night."
    },
    {
        "titulo_original": "Stranger Things",
        "tmdb_id": 66732,
        "tipo": "tv_episode",
        "season": 4,
        "episode": 1,
        "idioma": "es",
        "pais": "ES",
        "nome_idioma": "Spanish",
        "titulo_traduzido": "El club Fuego Infernal",
        "sinopse_traduzida": "Ce no puede defenderse de los abusones de su nuevo instituto. Joyce abre un paquete muy misterioso. En Hawkins, alguien inesperado arrasa en el club Fuego Infernal."
    },
    {
        "titulo_original": "Stranger Things",
        "tmdb_id": 66732,
        "tipo": "tv_episode",
        "season": 4,
        "episode": 1,
        "idioma": "es",
        "pais": "MX",
        "nome_idioma": "Spanish",
        "titulo_traduzido": "El club Fuego Infernal",
        "sinopse_traduzida": "Ce no puede defenderse de los abusones de su nuevo instituto. Joyce abre un paquete muy misterioso. En Hawkins, alguien inesperado arrasa en el club Fuego Infernal."
    },
    {
        "titulo_original": "Stranger Things",
        "tmdb_id": 66732,
        "tipo": "tv_episode",
        "season": 4,
        "episode": 1,
        "idioma": "eu",
        "pais": "ES",
        "nome_idioma": "Basque",
        "titulo_traduzido": "",
        "sinopse_traduzida": ""
    },
    {
        "titulo_original": "Stranger Things",
        "tmdb_id": 66732,
        "tipo": "tv_episode",
        "season": 4,
        "episode": 1,
        "idioma": "fa",
        "pais": "IR",
        "nome_idioma": "Persian",
        "titulo_traduzido": "",
        "sinopse_traduzida": ""
    },
    {
        "titulo_original": "Stranger Things",
        "tmdb_id": 66732,
        "tipo": "tv_episode",
        "season": 4,
        "episode": 1,
        "idioma": "fi",
        "pais": "FI",
        "nome_idioma": "Finnish",
        "titulo_traduzido": "Ensimmäinen luku: Hornantuli-kerho",
        "sinopse_traduzida": "El joutuu kiusatuksi uudessa koulussaan, muttei pysty puolustamaan itseään. Joyce avaa salaperäisen paketin. Hawkinsissa ärhäkkä pelaaja muuttaa D & D -illan suunnan."
    },
    {
        "titulo_original": "Stranger Things",
        "tmdb_id": 66732,
        "tipo": "tv_episode",
        "season": 4,
        "episode": 1,
        "idioma": "fr",
        "pais": "FR",
        "nome_idioma": "French",
        "titulo_traduzido": "Chapitre un : Le Club du feu de l'Enfer",
        "sinopse_traduzida": "Harcelée dans son nouveau lycée, Elfe est dans l'incapacité de riposter. Joyce ouvre un mystérieux paquet. À Hawkins, une joueuse bagarreuse enflamme la soirée D&D."
    },
    {
        "titulo_original": "Stranger Things",
        "tmdb_id": 66732,
        "tipo": "tv_episode",
        "season": 4,
        "episode": 1,
        "idioma": "fr",
        "pais": "CA",
        "nome_idioma": "French",
        "titulo_traduzido": "Chapitre un : Le club du Feu de l'enfer",
        "sinopse_traduzida": "Des brutes s'en prennent à Elfe à l'école, mais elle ne peut pas se défendre. Joyce ouvre un mystérieux paquet. Une soirée intense de Donjons et Dragons a lieu à Hawkins."
    },
    {
        "titulo_original": "Stranger Things",
        "tmdb_id": 66732,
        "tipo": "tv_episode",
        "season": 4,
        "episode": 1,
        "idioma": "he",
        "pais": "IL",
        "nome_idioma": "Hebrew",
        "titulo_traduzido": "פרק 1: מועדון הלפייר",
        "sinopse_traduzida": "אל סובלת מהצקות בבית הספר החדש, אבל היא לא יכולה להשיב מלחמה. ג'ויס פותחת חבילה מסתורית. בהוקינס, שחקנית נחושה טורפת את הקלפים בערב של מבוכים ודרקונים."
    },
    {
        "titulo_original": "Stranger Things",
        "tmdb_id": 66732,
        "tipo": "tv_episode",
        "season": 4,
        "episode": 1,
        "idioma": "hr",
        "pais": "HR",
        "nome_idioma": "Croatian",
        "titulo_traduzido": "Prvo poglavlje: The Hellfire Club",
        "sinopse_traduzida": "Nasilnici muče Je u novoj školi, ali ona im ne smije uzvratiti udarac. Joyce otvori tajanstveni paket. U Hawkinsku snalažljiva igračica unese nemir u večer D&D-a."
    },
    {
        "titulo_original": "Stranger Things",
        "tmdb_id": 66732,
        "tipo": "tv_episode",
        "season": 4,
        "episode": 1,
        "idioma": "hu",
        "pais": "HU",
        "nome_idioma": "Hungarian",
        "titulo_traduzido": "Első fejezet: A Pokol Tüze Klub",
        "sinopse_traduzida": "Tizit piszkálják a többiek az új iskolában, de nem tud visszavágni. Joyce kinyit egy titokzatos csomagot. Hawkinsban egy harcias játékos rázza fel a D&D éjszakát."
    },
    {
        "titulo_original": "Stranger Things",
        "tmdb_id": 66732,
        "tipo": "tv_episode",
        "season": 4,
        "episode": 1,
        "idioma": "id",
        "pais": "ID",
        "nome_idioma": "Indonesian",
        "titulo_traduzido": "Bab Satu: Klub Hellfire",
        "sinopse_traduzida": "El dirundung di sekolah barunya, tetapi ia tak bisa melawan. Joyce membuka paket misterius. Di Hawkins, seorang pemain tangguh mengguncang malam D&D."
    },
    {
        "titulo_original": "Stranger Things",
        "tmdb_id": 66732,
        "tipo": "tv_episode",
        "season": 4,
        "episode": 1,
        "idioma": "it",
        "pais": "IT",
        "nome_idioma": "Italian",
        "titulo_traduzido": "Capitolo uno: Hellfire Club",
        "sinopse_traduzida": "Undi non riesce a difendersi dai bulli nella nuova scuola. Joyce apre un misterioso pacchetto. A Hawkins una giocatrice da strapazzo sconvolge la serata al club di D&D."
    },
    {
        "titulo_original": "Stranger Things",
        "tmdb_id": 66732,
        "tipo": "tv_episode",
        "season": 4,
        "episode": 1,
        "idioma": "ja",
        "pais": "JP",
        "nome_idioma": "Japanese",
        "titulo_traduzido": "第1章 ヘルファイア・クラブ",
        "sinopse_traduzida": "新しい学校でいじめられても反撃できないエル。ジョイスは不気味な小包を受け取る。ホーキンスで、肝の据わったプレイヤーがD&Dゲームを盛り上げる。"
    },
    {
        "titulo_original": "Stranger Things",
        "tmdb_id": 66732,
        "tipo": "tv_episode",
        "season": 4,
        "episode": 1,
        "idioma": "ka",
        "pais": "GE",
        "nome_idioma": "Georgian",
        "titulo_traduzido": "",
        "sinopse_traduzida": ""
    },
    {
        "titulo_original": "Stranger Things",
        "tmdb_id": 66732,
        "tipo": "tv_episode",
        "season": 4,
        "episode": 1,
        "idioma": "ko",
        "pais": "KR",
        "nome_idioma": "Korean",
        "titulo_traduzido": "그들의 클럽",
        "sinopse_traduzida": "새 학교로 전학 간 엘. 친구들에게 괴롭힘을 당하지만, 반격할 수가 없다. 조이스는 정체불명의 택배를 받아들고, 호킨스에서는 초짜 플레이어가 D&D 토너먼트를 뒤흔든다."
    },
    {
        "titulo_original": "Stranger Things",
        "tmdb_id": 66732,
        "tipo": "tv_episode",
        "season": 4,
        "episode": 1,
        "idioma": "lt",
        "pais": "LT",
        "nome_idioma": "Lithuanian",
        "titulo_traduzido": "",
        "sinopse_traduzida": ""
    },
    {
        "titulo_original": "Stranger Things",
        "tmdb_id": 66732,
        "tipo": "tv_episode",
        "season": 4,
        "episode": 1,
        "idioma": "nl",
        "pais": "NL",
        "nome_idioma": "Dutch",
        "titulo_traduzido": "Hoofdstuk een: The Hellfire Club",
        "sinopse_traduzida": "El heeft pestkoppen op haar nieuwe school, maar ze kan niets terugdoen. Joyce opent een mysterieus pakket. In Hawkins schopt een fanatieke speler de D&D-avond in de war."
    },
    {
        "titulo_original": "Stranger Things",
        "tmdb_id": 66732,
        "tipo": "tv_episode",
        "season": 4,
        "episode": 1,
        "idioma": "no",
        "pais": "NO",
        "nome_idioma": "Norwegian",
        "titulo_traduzido": "Kapittel én: Hellfire-klubben",
        "sinopse_traduzida": "Ell blir mobbet på den nye skolen, men kan ikke gjøre motstand. Joyce åpner en mystisk pakke. I Hawkins skaper en tøff spiller oppstyr på D&D-kvelden."
    },
    {
        "titulo_original": "Stranger Things",
        "tmdb_id": 66732,
        "tipo": "tv_episode",
        "season": 4,
        "episode": 1,
        "idioma": "pl",
        "pais": "PL",
        "nome_idioma": "Polish",
        "titulo_traduzido": "Rozdział pierwszy: Klub Ognia Piekielnego",
        "sinopse_traduzida": "W nowej szkole Jedenastka nie potrafi przeciwstawić się łobuzom. Joyce otwiera tajemniczą przesyłkę. W Hawkins zuchwała graczka wstrząsa partią Dungeons & Dragons."
    },
    {
        "titulo_original": "Stranger Things",
        "tmdb_id": 66732,
        "tipo": "tv_episode",
        "season": 4,
        "episode": 1,
        "idioma": "pt",
        "pais": "BR",
        "nome_idioma": "Portuguese",
        "titulo_traduzido": "Capítulo um: O Clube Hellfire",
        "sinopse_traduzida": "Na nova escola, On precisa aprender a lidar com os valentões. Joyce abre um pacote misterioso. Em Hawkins, uma jogadora atrevida agita a noite de D&D."
    },
    {
        "titulo_original": "Stranger Things",
        "tmdb_id": 66732,
        "tipo": "tv_episode",
        "season": 4,
        "episode": 1,
        "idioma": "pt",
        "pais": "PT",
        "nome_idioma": "Portuguese",
        "titulo_traduzido": "Capítulo 1: O clube",
        "sinopse_traduzida": "Onze é alvo de bullying na nova escola, mas não pode ripostar. Joyce recebe uma encomenda misteriosa. Em Hawkins, alguém agita a noite de D&D."
    },
    {
        "titulo_original": "Stranger Things",
        "tmdb_id": 66732,
        "tipo": "tv_episode",
        "season": 4,
        "episode": 1,
        "idioma": "ro",
        "pais": "RO",
        "nome_idioma": "Romanian",
        "titulo_traduzido": "Capitolul unu: Clubul Hellfire",
        "sinopse_traduzida": "Unșpe este hărțuită la noua școală, dar nu poate riposta. Joyce deschide un colet misterios. La Hawkins, o jucătoare bătăioasă agită spiritele în seara de la clubul D&D."
    },
    {
        "titulo_original": "Stranger Things",
        "tmdb_id": 66732,
        "tipo": "tv_episode",
        "season": 4,
        "episode": 1,
        "idioma": "ru",
        "pais": "RU",
        "nome_idioma": "Russian",
        "titulo_traduzido": "Первая глава. Адский клуб",
        "sinopse_traduzida": "Оди не может противостоять нападкам ребят в новой школе. Джойс открывает загадочную посылку. В Хоукинсе вздорный игрок делает сенсационный ход в «Подземельях и драконах»."
    },
    {
        "titulo_original": "Stranger Things",
        "tmdb_id": 66732,
        "tipo": "tv_episode",
        "season": 4,
        "episode": 1,
        "idioma": "sk",
        "pais": "SK",
        "nome_idioma": "Slovak",
        "titulo_traduzido": "Kapitola prvá: Klub Hellfire",
        "sinopse_traduzida": "El na novej škole šikanujú a ona sa nemá ako brániť. Joyce otvára tajomný balíček. V Hawkinse zamieša hubatá hráčka poradím účastníkov nočnej hernej seansy."
    },
    {
        "titulo_original": "Stranger Things",
        "tmdb_id": 66732,
        "tipo": "tv_episode",
        "season": 4,
        "episode": 1,
        "idioma": "sr",
        "pais": "RS",
        "nome_idioma": "Serbian",
        "titulo_traduzido": "",
        "sinopse_traduzida": ""
    },
    {
        "titulo_original": "Stranger Things",
        "tmdb_id": 66732,
        "tipo": "tv_episode",
        "season": 4,
        "episode": 1,
        "idioma": "sv",
        "pais": "SE",
        "nome_idioma": "Swedish",
        "titulo_traduzido": "Del ett: Hellfire-klubben",
        "sinopse_traduzida": "El kan inte göra något åt mobbarna på sin nya skola, Joyce öppnar ett mystiskt paket och en ny spelare rör om i grytan när det spelas Drakar och demoner i Hawkins."
    },
    {
        "titulo_original": "Stranger Things",
        "tmdb_id": 66732,
        "tipo": "tv_episode",
        "season": 4,
        "episode": 1,
        "idioma": "th",
        "pais": "TH",
        "nome_idioma": "Thai",
        "titulo_traduzido": "บทที่ 1: เฮลไฟร์คลับ",
        "sinopse_traduzida": "แอลตกเป็นเป้านิ่งให้นักเรียนที่โรงเรียนใหม่กลั่นแกล้งและไม่อาจตอบโต้ จอยซ์ได้รับพัสดุลึกลับ ส่วนผู้เล่นขาลุยมาสร้างปรากฏการณ์ให้คืนนัดเล่นดันเจียนแอนด์ดรากอนในฮอว์กินส์"
    },
    {
        "titulo_original": "Stranger Things",
        "tmdb_id": 66732,
        "tipo": "tv_episode",
        "season": 4,
        "episode": 1,
        "idioma": "tr",
        "pais": "TR",
        "nome_idioma": "Turkish",
        "titulo_traduzido": "1. Bölüm: Hellfire Kulübü",
        "sinopse_traduzida": "El, yeni okulundaki zorbalara karşı kendini korumakta güçlük çekerken Joyce gizemli bir paket alır. Hawkins'de ise amatör bir oyuncu D&D gecesini alt üst eder."
    },
    {
        "titulo_original": "Stranger Things",
        "tmdb_id": 66732,
        "tipo": "tv_episode",
        "season": 4,
        "episode": 1,
        "idioma": "uk",
        "pais": "UA",
        "nome_idioma": "Ukrainian",
        "titulo_traduzido": "Глава 1. Клуб пекельного полум’я",
        "sinopse_traduzida": "У школі над Од знущаються, а вона не може дати відсіч. Джойс відкриває загадкову посилку. У Гокінсі декому вдається викликати переполох під час гри."
    },
    {
        "titulo_original": "Stranger Things",
        "tmdb_id": 66732,
        "tipo": "tv_episode",
        "season": 4,
        "episode": 1,
        "idioma": "uz",
        "pais": "UZ",
        "nome_idioma": "Uzbek",
        "titulo_traduzido": "",
        "sinopse_traduzida": ""
    },
    {
        "titulo_original": "Stranger Things",
        "tmdb_id": 66732,
        "tipo": "tv_episode",
        "season": 4,
        "episode": 1,
        "idioma": "vi",
        "pais": "VN",
        "nome_idioma": "Vietnamese",
        "titulo_traduzido": "Tập một: Câu lạc bộ Hellfire",
        "sinopse_traduzida": "El bị bắt nạt ở trường. Joyce mở một gói hàng bí ẩn. Một người chơi hiếu thắng khuấy động đêm chơi D&D. Cảnh báo: Có cảnh bạo lực liên quan đến trẻ em."
    },
    {
        "titulo_original": "Stranger Things",
        "tmdb_id": 66732,
        "tipo": "tv_episode",
        "season": 4,
        "episode": 1,
        "idioma": "zh",
        "pais": "CN",
        "nome_idioma": "Mandarin",
        "titulo_traduzido": "地狱火俱乐部",
        "sinopse_traduzida": "艾尔在新学校被欺负，却无法反击。乔伊斯打开一个神秘包裹。在霍金斯，一个好斗的玩家撼动了龙与地下城之夜。"
    },
    {
        "titulo_original": "Stranger Things",
        "tmdb_id": 66732,
        "tipo": "tv_episode",
        "season": 4,
        "episode": 1,
        "idioma": "zh",
        "pais": "TW",
        "nome_idioma": "Mandarin",
        "titulo_traduzido": "第 1 章：地獄火俱樂部",
        "sinopse_traduzida": "小伊在新學校被人欺負，卻無力還手。喬絲打開神秘包裹。霍金斯一名好勝的玩家在《龍與地下城》之夜震驚全場。"
    },
    {
        "titulo_original": "Stranger Things",
        "tmdb_id": 66732,
        "tipo": "tv_episode",
        "season": 4,
        "episode": 1,
        "idioma": "so",
        "pais": "SO",
        "nome_idioma": "Somali",
        "titulo_traduzido": "",
        "sinopse_traduzida": ""
    },
    {
        "titulo_original": "Stranger Things",
        "tmdb_id": 66732,
        "tipo": "tv_episode",
        "season": 4,
        "episode": 1,
        "idioma": "bn",
        "pais": "BD",
        "nome_idioma": "Bengali",
        "titulo_traduzido": "",
        "sinopse_traduzida": ""
    },
    {
        "titulo_original": "Stranger Things",
        "tmdb_id": 66732,
        "tipo": "tv_episode",
        "season": 4,
        "episode": 1,
        "idioma": "nl",
        "pais": "BE",
        "nome_idioma": "Dutch",
        "titulo_traduzido": "Aflevering 1 : The Hellfire Club",
        "sinopse_traduzida": "El wordt gepest op school. Joyce opent een mysterieus pakketje. En een vechtersbaasje zorgt voor opschudding op de D&D-avond."
    },
    {
        "titulo_original": "Stranger Things",
        "tmdb_id": 66732,
        "tipo": "tv_episode",
        "season": 4,
        "episode": 1,
        "idioma": "zh",
        "pais": "HK",
        "nome_idioma": "Mandarin",
        "titulo_traduzido": "第 1 章：地獄火俱樂部",
        "sinopse_traduzida": "小伊在新學校被人欺負，卻無力還手。喬絲打開神秘包裹。霍金斯一名好勝的玩家在《龍與地下城》之夜震驚全場。"
    },
    {
        "titulo_original": "Stranger Things",
        "tmdb_id": 66732,
        "tipo": "tv_episode",
        "season": 4,
        "episode": 1,
        "idioma": "zh",
        "pais": "SG",
        "nome_idioma": "Mandarin",
        "titulo_traduzido": "第一集：地狱火俱乐部",
        "sinopse_traduzida": "艾尔在新学校被欺负，却无法反击。乔伊斯打开一个神秘包裹。在霍金斯，一个好斗的玩家撼动了龙与地下城之夜。"
    },
    {
        "titulo_original": "Stranger Things",
        "tmdb_id": 66732,
        "tipo": "tv_episode",
        "season": 4,
        "episode": 1,
        "idioma": "sl",
        "pais": "SI",
        "nome_idioma": "Slovenian",
        "titulo_traduzido": "",
        "sinopse_traduzida": ""
    },
    {
        "titulo_original": "Stranger Things",
        "tmdb_id": 66732,
        "tipo": "tv_episode",
        "season": 4,
        "episode": 1,
        "idioma": "hi",
        "pais": "IN",
        "nome_idioma": "Hindi",
        "titulo_traduzido": "चैप्टर एक: द हेलफ़ायर क्लब",
        "sinopse_traduzida": "एल को उसके नए स्कूल में सताया जाता है, पर वह पलटकर लड़ नहीं पाती. जॉयस एक रहस्यमयी पैकेज खोलती है. उधर हॉकिंस में, एक बेढंगी प्लेयर डी एंड डी नाइट में तहलका मचा देती है."
    },
    {
        "titulo_original": "Stranger Things",
        "tmdb_id": 66732,
        "tipo": "tv_episode",
        "season": 4,
        "episode": 1,
        "idioma": "ms",
        "pais": "MY",
        "nome_idioma": "Malay",
        "titulo_traduzido": "Babak Satu: Kelab Api Neraka",
        "sinopse_traduzida": "El dibuli di sekolah baharunya, tetapi dia tidak boleh melawan. Joyce membuka pakej yang misteri. Di Hawkins, seorang pemain berazam tinggi menggemparkan malam D&D."
    },
    {
        "titulo_original": "Stranger Things",
        "tmdb_id": 66732,
        "tipo": "tv_episode",
        "season": 4,
        "episode": 1,
        "idioma": "tl",
        "pais": "PH",
        "nome_idioma": "Tagalog",
        "titulo_traduzido": "Chapter One: Ang Hellfire Club",
        "sinopse_traduzida": "Nabu-bully si El sa school. May binuksang misteryosong package si Joyce. Niyanig ng determinadong player ang D&D night. Babala: May graphic na karahasan na may mga bata."
    },
    {
        "titulo_original": "Stranger Things",
        "tmdb_id": 66732,
        "tipo": "tv_episode",
        "season": 4,
        "episode": 1,
        "idioma": "lv",
        "pais": "LV",
        "nome_idioma": "Latvian",
        "titulo_traduzido": "",
        "sinopse_traduzida": ""
    },
    {
        "titulo_original": "Stranger Things",
        "tmdb_id": 66732,
        "tipo": "tv_episode",
        "season": 4,
        "episode": 1,
        "idioma": "de",
        "pais": "AT",
        "nome_idioma": "German",
        "titulo_traduzido": "",
        "sinopse_traduzida": ""
    }
]