{
    "id": 9615,
    "type": "movie",
    "title": "The Fast and the Furious: Tokyo Drift",
    "original_title": "The Fast and the Furious: Tokyo Drift",
    "release_date": "2006-06-03",
    "overview": "In order to avoid a jail sentence, Sean Boswell heads to Tokyo to live with his military father. In a low-rent section of the city, Shaun gets caught up in the underground world of drift racing",
    "vote_average": 6.532,
    "popularity": 2.0815,
    "genres": [
        "Action",
        "Crime",
        "Drama",
        "Thriller"
    ],
    "runtime": 104,
    "number_of_seasons": null,
    "status": "Released",
    "cast": [
        {
            "id": 155,
            "name": "Lucas Black",
            "character": "Sean Boswell"
        },
        {
            "id": 116277,
            "name": "Nathalie Kelley",
            "character": "Neela"
        },
        {
            "id": 61697,
            "name": "Sung Kang",
            "character": "Han Lue"
        },
        {
            "id": 58197,
            "name": "Shad Moss",
            "character": "Twinkie"
        },
        {
            "id": 116278,
            "name": "Brian Tee",
            "character": "D.K."
        },
        {
            "id": 24200,
            "name": "Leonardo Nam",
            "character": "Morimoto"
        },
        {
            "id": 80978,
            "name": "Brian Goodman",
            "character": "Major Boswell"
        },
        {
            "id": 52477,
            "name": "Zachery Ty Bryan",
            "character": "Clay"
        },
        {
            "id": 88677,
            "name": "Nikki Griffin",
            "character": "Cindy (Clay's Girlfriend)"
        },
        {
            "id": 162367,
            "name": "Jason Tobin",
            "character": "Earl"
        }
    ],
    "directors": [
        {
            "id": 58189,
            "name": "Justin Lin"
        }
    ],
    "_note": "All data in English"
}